Workbook

Sheet Task Backlog
A1: ID | B1: Category | C1: Task | D1: Description | E1: Best Practice Ref | F1: Priority | G1: Effort (Days) | H1: Impact (1-5) | I1: Feasibility (1-5) | J1: Score | K1: Phase | L1: Status | M1: Dependencies | N1: Owner | O1: Notes
A2: ML-01 | B2: Micro Loop | C2: Design "Survey Run" pre-level mechanic | D2: 30-second train flyover that reveals terrain/cities before each level starts, delivering instant visual reward | E2: BP#1: First Fun | F2: Critical | G2: 5 | H2: 5 | I2: 4 | J2: =H2*I2 -> 20 | K2: Phase 1 | L2: Not Started | M2: - | O2: Key D1 retention driver
A3: ML-02 | B3: Micro Loop | C3: Design track-laying puzzle mini-game | D3: Quick puzzle: connect two cities with minimum cost track. Earns starting bonus. Teaches core mechanic in 60s | E3: BP#1: First Fun | F3: Critical | G3: 8 | H3: 5 | I3: 3 | J3: =H3*I3 -> 15 | K3: Phase 1 | L3: Not Started | M3: - | O3: Alternative to ML-01; pick one or both
A4: ML-03 | B4: Micro Loop | C4: Pre-place starter train on Levels 1-5 | D4: First 5 levels begin with a running train on a short route so players see revenue ticking before they build anything | E4: BP#1: First Fun | F4: Critical | G4: 3 | H4: 5 | I4: 5 | J4: =H4*I4 -> 25 | K4: Phase 1 | L4: Not Started | M4: - | O4: Lowest effort, highest impact first-fun fix
A5: ML-04 | B5: Micro Loop | C5: Redesign first 60 seconds of Level 1 | D5: Full FTUE redesign: player sees train running → prompted to expand route → instant positive feedback | E5: BP#1: First Fun | F5: Critical | G5: 5 | H5: 5 | I5: 4 | J5: =H5*I5 -> 20 | K5: Phase 1 | L5: Not Started | M5: ML-03 | O5: Depends on ML-03 being implemented first
A6: EC-01 | B6: Economy | C6: Introduce premium currency (Gold Rivets) | D6: Rare currency earned via achievements/milestones, purchasable $0.99-$4.99. Spent on cosmetics, RP boosters, convenience | E6: BP#2: Dual Currency | F6: High | G6: 10 | H6: 5 | I6: 3 | J6: =H6*I6 -> 15 | K6: Phase 1 | L6: Not Started | M6: - | O6: Core monetization enabler
A7: EC-02 | B7: Economy | C7: Design faucet-drain balance model | D7: Spreadsheet model mapping all soft ($), hard (Rivets), and RP sources/sinks with target ratios per chapter | E7: BP#2: Dual Currency | F7: High | G7: 5 | H7: 4 | I7: 4 | J7: =H7*I7 -> 16 | K7: Phase 1 | L7: Not Started | M7: EC-01 | O7: Use Machinations or spreadsheet sim
A8: EC-03 | B8: Economy | C8: Resolve cross-document number inconsistencies | D8: Fix starting funds ($5K-$15K vs $30K-$70K), RP values (20/35/50 vs 40/70/100), mountain cost (3x vs 4x), hex orientation | E8: GDD Review §8 | F8: Critical | G8: 2 | H8: 4 | I8: 5 | J8: =H8*I8 -> 20 | K8: Phase 1 | L8: Not Started | M8: - | O8: Block other economy work until resolved
A9: EC-04 | B9: Economy | C9: Soften maintenance era scaling | D9: Change 1.5x per-era multiplier to 1.2x OR decouple from time and tie to player tech choices | E9: GDD Review §3 | F9: Medium | G9: 3 | H9: 3 | I9: 5 | J9: =H9*I9 -> 15 | K9: Phase 2 | L9: Not Started | M9: EC-03 | O9: Reduces punishment for slow players
A10: EC-05 | B10: Economy | C10: Increase train retirement refund | D10: Raise from 25% to 40-50% refund, at least in Chapter 1. Reduces punishment for misclicks on mobile | E10: GDD Review §3 | F10: Medium | G10: 1 | H10: 3 | I10: 5 | J10: =H10*I10 -> 15 | K10: Phase 1 | L10: Not Started | M10: - | O10: Quick win, big UX improvement
A11: EC-06 | B11: Economy | C11: Make T1 upgrades more impactful | D11: Reduce cost to 30-40 RP OR increase effect to 20-25%. First purchase must feel like a power-up, not a rounding error | E11: GDD Review §4 | F11: High | G11: 2 | H11: 4 | I11: 5 | J11: =H11*I11 -> 20 | K11: Phase 1 | L11: Not Started | M11: - | O11: Critical for meta-loop first impression
A12: MN-01 | B12: Monetization | C12: Design Engineer's Pass (Season Pass) | D12: $1.99/month: 2x RP, exclusive train skin, 3 bonus levels, profile badge. Non-pay-to-win recurring revenue | E12: BP#3: Time Compression | F12: High | G12: 8 | H12: 5 | I12: 3 | J12: =H12*I12 -> 15 | K12: Phase 2 | L12: Not Started | M12: EC-01 | O12: Primary recurring revenue stream
A13: MN-02 | B13: Monetization | C13: Deepen cosmetic catalog | D13: Expand from ~$10 ceiling to $30+: more train skins, animated effects, station themes, conductor avatars, trail effects | E13: BP#3: Time Compression | F13: High | G13: 12 | H13: 4 | I13: 3 | J13: =H13*I13 -> 12 | K13: Phase 2 | L13: Not Started | M13: - | O13: Current catalog too thin for sustainability
... A44: AI-04 | B44: Analytics | C44: Plan localization pipeline | D44: String extraction, translation workflow, RTL support assessment. Priority markets: Japan, Korea, Germany, France | E44: GDD Review §9 | F44: Low | G44: 5 | H44: 3 | I44: 3 | J44: =H44*I44 -> 9 | K44: Phase 3 | L44: Not Started | M44: - | O44: Revenue unlock for international markets

Sheet Dashboard
B2: Iron Dominion — Implementation Dashboard
B4: Total Tasks | C4: Critical | D4: High | E4: Medium | F4: Low | G4: Total Effort (Days)
B5: =COUNTA('Task Backlog'!A2:A44) -> 43 | C5: =COUNTIF('Task Backlog'!F2:F44,"Critical") -> 6 | D5: =COUNTIF('Task Backlog'!F2:F44,"High") -> 15 | E5: =COUNTIF('Task Backlog'!F2:F44,"Medium") -> 17 | F5: =COUNTIF('Task Backlog'!F2:F44,"Low") -> 5 | G5: =SUM('Task Backlog'!G2:G44) -> 232
B8: Tasks by Category
B9: Category | C9: Count | D9: Effort (Days) | E9: Avg Score
B10: Micro Loop | C10: =COUNTIF('Task Backlog'!B2:B44,B10) -> 4 | D10: =SUMIF('Task Backlog'!B2:B44,B10,'Task Backlog'!G2:G44) -> 21 | E10: =IFERROR(AVERAGEIF('Task Backlog'!B2:B44,B10,'Task Backlog'!J2:J44),"-") -> 20
B11: Economy | C11: =COUNTIF('Task Backlog'!B2:B44,B11) -> 6 | D11: =SUMIF('Task Backlog'!B2:B44,B11,'Task Backlog'!G2:G44) -> 23 | E11: =IFERROR(AVERAGEIF('Task Backlog'!B2:B44,B11,'Task Backlog'!J2:J44),"-") -> 16.833333
B12: Monetization | C12: =COUNTIF('Task Backlog'!B2:B44,B12) -> 4 | D12: =SUMIF('Task Backlog'!B2:B44,B12,'Task Backlog'!G2:G44) -> 28 | E12: =IFERROR(AVERAGEIF('Task Backlog'!B2:B44,B12,'Task Backlog'!J2:J44),"-") -> 15.5
B13: Session Design | C13: =COUNTIF('Task Backlog'!B2:B44,B13) -> 4 | D13: =SUMIF('Task Backlog'!B2:B44,B13,'Task Backlog'!G2:G44) -> 20 | E13: =IFERROR(AVERAGEIF('Task Backlog'!B2:B44,B13,'Task Backlog'!J2:J44),"-") -> 12.75
B14: Social | C14: =COUNTIF('Task Backlog'!B2:B44,B14) -> 5 | D14: =SUMIF('Task Backlog'!B2:B44,B14,'Task Backlog'!G2:G44) -> 38 | E14: =IFERROR(AVERAGEIF('Task Backlog'!B2:B44,B14,'Task Backlog'!J2:J44),"-") -> 12
B15: Variable Rewards | C15: =COUNTIF('Task Backlog'!B2:B44,B15) -> 3 | D15: =SUMIF('Task Backlog'!B2:B44,B15,'Task Backlog'!G2:G44) -> 13 | E15: =IFERROR(AVERAGEIF('Task Backlog'!B2:B44,B15,'Task Backlog'!J2:J44),"-") -> 14.666667
B16: LiveOps | C16: =COUNTIF('Task Backlog'!B2:B44,B16) -> 4 | D16: =SUMIF('Task Backlog'!B2:B44,B16,'Task Backlog'!G2:G44) -> 29 | E16: =IFERROR(AVERAGEIF('Task Backlog'!B2:B44,B16,'Task Backlog'!J2:J44),"-") -> 11.5
B17: Onboarding | C17: =COUNTIF('Task Backlog'!B2:B44,B17) -> 4 | D17: =SUMIF('Task Backlog'!B2:B44,B17,'Task Backlog'!G2:G44) -> 17 | E17: =IFERROR(AVERAGEIF('Task Backlog'!B2:B44,B17,'Task Backlog'!J2:J44),"-") -> 16.75
B18: Level Design | C18: =COUNTIF('Task Backlog'!B2:B44,B18) -> 5 | D18: =SUMIF('Task Backlog'!B2:B44,B18,'Task Backlog'!G2:G44) -> 25 | E18: =IFERROR(AVERAGEIF('Task Backlog'!B2:B44,B18,'Task Backlog'!J2:J44),"-") -> 14
B19: Analytics | C19: =COUNTIF('Task Backlog'!B2:B44,B19) -> 4 | D19: =SUMIF('Task Backlog'!B2:B44,B19,'Task Backlog'!G2:G44) -> 18 | E19: =IFERROR(AVERAGEIF('Task Backlog'!B2:B44,B19,'Task Backlog'!J2:J44),"-") -> 12.5
B20: TOTAL | C20: =SUM(C10:C19) -> 43 | D20: =SUM(D10:D19) -> 232
B23: Tasks by Phase
B24: Phase | C24: Count | D24: Effort (Days) | E24: Critical | F24: High
B25: Phase 1 | C25: =COUNTIF('Task Backlog'!K2:K44,B25) -> 17 | D25: =SUMIF('Task Backlog'!K2:K44,B25,'Task Backlog'!G2:G44) -> 77 | E25: =COUNTIFS('Task Backlog'!K2:K44,B25,'Task Backlog'!F2:F44,"Critical") -> 6 | F25: =COUNTIFS('Task Backlog'!K2:K44,B25,'Task Backlog'!F2:F44,"High") -> 7
B26: Phase 2 | C26: =COUNTIF('Task Backlog'!K2:K44,B26) -> 19 | D26: =SUMIF('Task Backlog'!K2:K44,B26,'Task Backlog'!G2:G44) -> 100 | E26: =COUNTIFS('Task Backlog'!K2:K44,B26,'Task Backlog'!F2:F44,"Critical") -> 0 | F26: =COUNTIFS('Task Backlog'!K2:K44,B26,'Task Backlog'!F2:F44,"High") -> 8
B27: Phase 3 | C27: =COUNTIF('Task Backlog'!K2:K44,B27) -> 7 | D27: =SUMIF('Task Backlog'!K2:K44,B27,'Task Backlog'!G2:G44) -> 55 | E27: =COUNTIFS('Task Backlog'!K2:K44,B27,'Task Backlog'!F2:F44,"Critical") -> 0 | F27: =COUNTIFS('Task Backlog'!K2:K44,B27,'Task Backlog'!F2:F44,"High") -> 0

Sheet Phase Roadmap
B2: Implementation Roadmap
B4: PHASE 1: Foundation (Weeks 1-6)
B5: Goal | C5: Fix the first 60 seconds, resolve economy inconsistencies, enable monetization infrastructure
B7: Focus Area | C7: Key Deliverable | D7: Effort | E7: KPI Target | F7: Tasks
B8: First Fun | C8: Pre-placed trains + redesigned Level 1 FTUE | D8: 8 days | E8: Time to first reward < 30s | F8: ML-03, ML-04
B9: Economy Fix | C9: Single source of truth for all numbers | D9: 2 days | E9: Zero cross-doc conflicts | F9: EC-03
B10: Premium Currency | C10: Gold Rivets system designed + implemented | D10: 10 days | E10: Currency visible in Meta Hub | F10: EC-01, EC-02
B11: Upgrade Rebalance | C11: T1 upgrades feel impactful | D11: 2 days | E11: First upgrade purchase rate > 80% | F11: EC-06, EC-05
B12: Onboarding | C12: Progressive disclosure + Meta Hub tour | D12: 10 days | E12: D1 retention > 40% | F12: OB-01, OB-02, OB-03
B13: Chapter 2 Design | C13: Full level configs for conversion chapter | D13: 8 days | E13: Chapter 2 completion > 50% | F13: LD-01
B14: Analytics | C14: Event tracking + auto-save | D14: 8 days | E14: All key funnels tracked | F14: AI-01, AI-03
B15: Revenue Model | C15: Revised projections with new monetization | D15: 3 days | E15: Realistic financial plan | F15: MN-04
B18: PHASE 2: Retention & Revenue (Weeks 7-14)
B19: Goal | C19: Add session hooks, social features, variable rewards, and Season Pass to drive D7/D30 retention and recurring revenue
B21: Focus Area | C21: Key Deliverable | D21: Effort | E21: KPI Target | F21: Tasks
B22: Season Pass | C22: Engineer's Pass live with first season content | D22: 8 days | E22: 5% conversion in Month 1 | F22: MN-01
B23: Cosmetic Depth | C23: Catalog expanded to $30+ ceiling | D23: 12 days | E23: 10% cosmetic purchase rate | F23: MN-02, MN-03
B24: Idle Layer | C24: Railway Network passive RP generation | D24: 8 days | E24: 2+ daily sessions avg | F24: SD-01, SD-02, SD-03
B25: Social | C25: Ghost rivals + Endless leaderboard + share | D25: 15 days | E25: D30 retention > 12% | F25: SO-01, SO-02, SO-03
B26: Variable Rewards | C26: Bonus roll + random events + mystery chest | D26: 13 days | E26: Level replay rate +20% | F26: VR-01, VR-02, VR-03
B27: Daily Challenges | C27: Full daily challenge system live | D27: 8 days | E27: 70% of active players attempt daily | F27: LO-01
B28: Level Variety | C28: New objective types + Casual Mode | D28: 10 days | E28: Ch2-3 completion > 40% | F28: LD-02, LD-03
B29: Economy Tuning | C29: A/B test framework + maintenance rebalance | D29: 8 days | E29: Bankrupt rate < 15% | F29: AI-02, EC-04
B32: PHASE 3: Scale & Polish (Weeks 15-22)
B33: Goal | C33: LiveOps pipeline, community features, internationalization, and long-tail engagement systems
B35: Focus Area | C35: Key Deliverable | D35: Effort | E35: KPI Target | F35: Tasks
B36: LiveOps | C36: Seasonal themes + quarterly season reset | D36: 18 days | E36: MAU stable Month 3+ | F36: LO-02, LO-03, LO-04
B37: Community | C37: Weekly challenge + alliance-lite (if warranted) | D37: 23 days | E37: 30% of DAU in social feature | F37: SO-04, SO-05
B38: Long-tail | C38: Prestige system + career rank polish | D38: 7 days | E38: 10% prestige adoption | F38: LD-05, LD-04, SD-04
B39: International | C39: Localization pipeline for 4 markets | D39: 5 days | E39: 15% revenue from non-English | F39: AI-04

Sheet Best Practice Ref
B2: Best Practice Reference Table
B4: ID | C4: Best Practice | D4: Summary | E4: Iron Dominion Gap | F4: Source
B5: BP#1 | C5: First Fun Principle | D5: First 60s must deliver instant gratification via simple, self-contained mechanic | E5: Large: 2-4 min build phase before first reward | F5: GameMakers, GameRefinery
B6: BP#2 | C6: Dual-Currency Economy | D6: Soft + Hard + Social currencies with balanced faucets/drains | E6: Large: Only $ and RP, no premium or social currency | F6: Lost Garden, Kallist
B7: BP#3 | C7: Time Compression Monetization | D7: Speed-ups as primary revenue driver, open-ended LTV | E7: Large: One-time $3.99, capped LTV at ~$14 | F7: ThinkingData, DoF
B8: BP#4 | C8: Social/Alliance Systems | D8: Alliance within 48hrs, daily social obligations, alliance shop | E8: Critical: Zero social features | F8: GameRefinery, ThinkingData
B9: BP#5 | C9: Hybridization | D9: Casual mechanic + 4X depth for broader audience | E9: Medium: Tycoon framing is good but no dedicated micro loop | F9: GameRefinery, Naavik
B10: BP#6 | C10: Multi-Cadence Sessions | D10: 3-5 daily sessions of varying length | E10: Large: Single 10-15 min session, no quick-check flow | F10: GameAnalytics
B11: BP#7 | C11: Event-Driven LiveOps | D11: 3-5 overlapping events at all times post-launch | E11: Large: Daily Challenges designed but not built, no other events | F11: DoF, GameRefinery
B12: BP#8 | C12: Progressive Disclosure | D12: Hide complexity for first hour, reveal over 7 days | E12: Medium: Full UI visible from start, tutorial covers 3 levels | F12: Last War analysis
B13: BP#9 | C13: Variable Rewards | D13: Mystery chests, random events, bonus rolls | E13: Medium: 100% deterministic rewards | F13: Player psych research
